pebblo_langchain/__init__.py
pebblo_langchain/langchain_community/__init__.py
pebblo_langchain/langchain_community/document_loaders/__init__.py
pebblo_langchain/langchain_community/document_loaders/pebblo.py
pebblo_langchain/langchain_community/utilities/__init__.py
pebblo_langchain/langchain_community/utilities/pebblo.py
pebblo_langchain-0.1.3.dist-info/LICENSE
pebblo_langchain-0.1.3.dist-info/METADATA
pebblo_langchain-0.1.3.dist-info/WHEEL
pebblo_langchain-0.1.3.dist-info/top_level.txt
pebblo_langchain-0.1.3.dist-info/RECORD
