Metadata-Version: 2.1
Name: pebblo-langchain
Version: 0.1.3
Summary: Pebblo Gen-AI Data Analyzer
Author-email: Pebblo Authors <pebblo@daxa.ai>
Maintainer-email: Pebblo Maintainer <pebblo@daxa.ai>
Project-URL: Homepage, https://github.com/daxa-ai/pebblo-langchain
Project-URL: Bug Reports, https://github.com/daxa-ai/pebblo-langchain/issues
Project-URL: Funding, https://donate.pypi.org
Project-URL: Source, https://github.com/daxa-ai/pebblo-langchain/
Keywords: langchain,ai,rag
Classifier: Development Status :: 3 - Alpha
Classifier: Intended Audience :: Developers
Classifier: Topic :: Software Development :: Build Tools
Classifier: License :: Other/Proprietary License
Classifier: Operating System :: OS Independent
Classifier: Programming Language :: Python :: 3
Classifier: Programming Language :: Python :: 3.7
Classifier: Programming Language :: Python :: 3.8
Classifier: Programming Language :: Python :: 3.9
Classifier: Programming Language :: Python :: 3.10
Classifier: Programming Language :: Python :: 3.11
Requires-Python: >=3.11
License-File: LICENSE
Requires-Dist: langchain >=0.1.2
Provides-Extra: dev
Requires-Dist: check-manifest ; extra == 'dev'
Provides-Extra: test
Requires-Dist: coverage ; extra == 'test'
